[
  {
    "title": "Netflix Clone App",
    "tools": [
      {
        "title": "React.js"
      },
      {
        "title": "Firebase"
      },
      {
        "title": "Git"
      },
      {
        "title": "Front-end project"
      }
    ],
    "img": "./assets/img/Netflix-clone.gif",
    "github": "https://github.com/Andjela24/netflix-clone",
    "website": "https://andjela-netflix-clone.web.app "
  },
  {
    "title": "E-tickets",
    "tools": [
      {
        "title": "C#"
      },
      {
        "title": "ASP.NET MVC"
      },
      {
        "title": "SQL"
      }
    ],
    "img": "./assets/img/Etickets.gif",
    "github": "https://github.com/andjela24/eTickets",
    "website": "https://andjela24.github.io/coming-soon/"
  },
  {
    "title": "Amazon Clone",
    "tools": [
      {
        "title": "React"
      },
      {
        "title": "Node.js"
      },
      {
        "title": "MongoDB"
      }
    ],
    "img": "./assets/img/Amazon-clone.gif",
    "github": "https://github.com/andjela24/amazon-clone",
    "website": "https://andjela24-amazon-clone.netlify.app/"
  },
  {
    "title": "Tetris Game",
    "tools": [
      {
        "title": "C#"
      },
      {
        "title": "Simple game"
      },
      {
        "title": "WPF Application"
      }
    ],
    "img": "./assets/img/Tetris.gif",
    "github": "https://github.com/andjela24/TetrisGame",
    "website": "https://andjela24.github.io/download-tetris/"
  }
]
